mapry_meta.py
mapry/__init__.py
mapry/indention.py
mapry/main.py
mapry/naming.py
mapry/parse.py
mapry/py.typed
mapry/schemas.py
mapry/strftime.py
mapry/validation.py
mapry/cpp/__init__.py
mapry/cpp/expr.py
mapry/cpp/jinja2_env.py
mapry/cpp/naming.py
mapry/cpp/validation.py
mapry/cpp/generate/__init__.py
mapry/cpp/generate/jsoncpp_header.py
mapry/cpp/generate/jsoncpp_impl.py
mapry/cpp/generate/parse_header.py
mapry/cpp/generate/parse_impl.py
mapry/cpp/generate/types_header.py
mapry/go/__init__.py
mapry/go/expr.py
mapry/go/jinja2_env.py
mapry/go/timeformat.py
mapry/go/validation.py
mapry/go/generate/__init__.py
mapry/go/generate/fromjsonable.py
mapry/go/generate/fromjsonable_test.py
mapry/go/generate/parse.py
mapry/go/generate/tojsonable.py
mapry/go/generate/tojsonable_test.py
mapry/go/generate/types.py
mapry/py/__init__.py
mapry/py/expr.py
mapry/py/jinja2_env.py
mapry/py/naming.py
mapry/py/validation.py
mapry/py/generate/__init__.py
mapry/py/generate/fromjsonable.py
mapry/py/generate/parse.py
mapry/py/generate/tojsonable.py
mapry/py/generate/types.py
mapry-1.0.0.1.data/scripts/mapry-to
mapry-1.0.0.1.dist-info/LICENSE.txt
mapry-1.0.0.1.dist-info/METADATA
mapry-1.0.0.1.dist-info/WHEEL
mapry-1.0.0.1.dist-info/top_level.txt
mapry-1.0.0.1.dist-info/RECORD
