Metadata-Version: 2.1
Name: mapry
Version: 1.0.0.1
Summary: Generate polyglot code for de/serializing object graphs from JSONable structures.
Home-page: http://github.com/Parquery/mapry
Author: Marko Ristin
Author-email: marko.ristin@gmail.com
License: License :: OSI Approved :: MIT License
Keywords: object mapping json serialization deserialization graph
Platform: UNKNOWN
Classifier: Development Status :: 5 - Production/Stable
Classifier: Intended Audience :: Developers
Classifier: License :: OSI Approved :: MIT License
Classifier: Programming Language :: Python :: 3.5
Classifier: Programming Language :: Python :: 3.6
Requires-Dist: typing-extensions
Requires-Dist: jsonschema (>=2.6.0)
Requires-Dist: lexery (>=1.0.1)
Requires-Dist: icontract (<3,>=2.0.5)
Requires-Dist: jinja2 (<3,>=2.10)
Provides-Extra: dev
Requires-Dist: coverage (<5,>=4.5.1) ; extra == 'dev'
Requires-Dist: pydocstyle (<4,>=3.0.0) ; extra == 'dev'
Requires-Dist: mypy (==0.670) ; extra == 'dev'
Requires-Dist: pylint (==2.3.0) ; extra == 'dev'
Requires-Dist: yapf (==0.27.0) ; extra == 'dev'
Requires-Dist: temppathlib (<2,>=1.0.3) ; extra == 'dev'
Requires-Dist: isort (<5,>=4.3.4) ; extra == 'dev'
Requires-Dist: twine (<2,>=1.12.1) ; extra == 'dev'
Requires-Dist: pyicontract-lint (<3,>=2.0.0) ; extra == 'dev'
Provides-Extra: testcpp
Requires-Dist: conan (<2,>=1.13.0) ; extra == 'testcpp'
Requires-Dist: temppathlib (<2,>=1.0.3) ; extra == 'testcpp'
Provides-Extra: testgo
Requires-Dist: temppathlib (<2,>=1.0.3) ; extra == 'testgo'
Provides-Extra: testpy
Requires-Dist: pytz (==2018.9) ; extra == 'testpy'
Requires-Dist: temppathlib (<2,>=1.0.3) ; extra == 'testpy'
Requires-Dist: mypy (==0.670) ; extra == 'testpy'
